fosslight_yocto/__init__.py
fosslight_yocto/_help.py
fosslight_yocto/_overwrite_yaml.py
fosslight_yocto/_package_item.py
fosslight_yocto/_write_result_file.py
fosslight_yocto/_zip_source_works.py
fosslight_yocto/create_oss_report_for_yocto.py
fosslight_yocto/parsing_meta_doubleopen.py
fosslight_yocto/parsing_yaml.py
fosslight_yocto-4.0.6.dist-info/LICENSE
fosslight_yocto-4.0.6.dist-info/METADATA
fosslight_yocto-4.0.6.dist-info/WHEEL
fosslight_yocto-4.0.6.dist-info/entry_points.txt
fosslight_yocto-4.0.6.dist-info/top_level.txt
fosslight_yocto-4.0.6.dist-info/RECORD
