Metadata-Version: 2.1
Name: fosslight-yocto
Version: 4.0.6
Summary: FOSSLight Yocto
Home-page: https://github.com/fosslight/fosslight_yocto_scanner
Download-URL: https://github.com/fosslight/fosslight_yocto_scanner
Author: LG Electronics
License: Apache-2.0
Classifier: License :: OSI Approved :: Apache Software License
Classifier: Programming Language :: Python :: 3
Classifier: Programming Language :: Python :: 3.10
Classifier: Programming Language :: Python :: 3.11
Classifier: Programming Language :: Python :: 3.12
Requires-Python: >=3.8
License-File: LICENSE
Requires-Dist: fosslight-util~=2.1.0
Requires-Dist: binaryornot
Requires-Dist: openpyxl
Requires-Dist: pandas
Requires-Dist: PyMySQL
Requires-Dist: python-dateutil
Requires-Dist: PyYAML
Requires-Dist: xlrd
Requires-Dist: XlsxWriter
Requires-Dist: parmap
Requires-Dist: ruamel.yaml
Requires-Dist: py-tlsh
Requires-Dist: tqdm
Requires-Dist: fosslight-binary~=5.1.0
Requires-Dist: fosslight-source~=2.1.0
